{"Date":"2020-10-14","Time":"20:06:43","Latitude":"0.0","Longitude":"0.0","Azimuth":"225.50576150603843","Pitch":"31.865089855630174","Roll":"-1.2326747619200547","Illuminance":"4394.0","Imei":"353498096777403","ScopeID":"1002","DeviceClass":"239","DeviceSubClass":"1002","DeviceName":"\/dev\/bus\/usb\/001\/002","VendorID":"4706","ProductID":"36864","ProductName":"GZ4304_1","SerialNumber":"00000000000000000000","ManufacturerName":"GAZO","ProduceText":"稲","MiscText":"","CommentText":"","Gain":"0","Exposure":"1250","ExposureMode":"1","Brightness":"50","Contrast":"50","Light":"4394.0","AutoExposure":"2"}