{"Date":"2020-10-09","Time":"21:45:03","Latitude":"0.0","Longitude":"0.0","Azimuth":"204.5988256641962","Pitch":"68.90507936610967","Roll":"-3.384517962526344","Illuminance":"78.0","Imei":"353498096777403","ScopeID":"1002","DeviceClass":"239","DeviceSubClass":"1002","DeviceName":"\/dev\/bus\/usb\/001\/002","VendorID":"4706","ProductID":"36864","ProductName":"GZ4304_1","SerialNumber":"00000000000000000000","ManufacturerName":"GAZO","ProduceText":"稲","MiscText":"","CommentText":"","Gain":"0","Exposure":"1250","ExposureMode":"1","Brightness":"50","Contrast":"50","Light":"78.0","AutoExposure":"2"}