{"Date":"2020-10-09","Time":"21:20:30","Latitude":"0.0","Longitude":"0.0","Azimuth":"189.02589873391875","Pitch":"89.41717563241181","Roll":"16.699243907432773","Illuminance":"66.0","Imei":"353498096777403","ScopeID":"1002","DeviceClass":"239","DeviceSubClass":"1002","DeviceName":"\/dev\/bus\/usb\/001\/002","VendorID":"4706","ProductID":"36864","ProductName":"GZ4304_1","SerialNumber":"00000000000000000000","ManufacturerName":"GAZO","ProduceText":"稲","MiscText":"","CommentText":"","Gain":"0","Exposure":"1250","ExposureMode":"1","Brightness":"50","Contrast":"50","Light":"66.0","AutoExposure":"2"}