{"Date":"2020-10-08","Time":"20:07:37","Latitude":"43.0852764","Longitude":"141.3336707","Azimuth":"51.90701297494155","Pitch":"61.291535800188164","Roll":"174.7207195730217","Illuminance":"140.0","Imei":"353498096777403","ScopeID":"1002","DeviceClass":"239","DeviceSubClass":"1002","DeviceName":"\/dev\/bus\/usb\/001\/002","VendorID":"4706","ProductID":"36864","ProductName":"GZ4304_1","SerialNumber":"00000000000000000000","ManufacturerName":"GAZO","ProduceText":"稲","MiscText":"","CommentText":"","Gain":"0","Exposure":"1250","ExposureMode":"1","Brightness":"50","Contrast":"50","Light":"140.0","AutoExposure":"2"}